yamlgrep/__init__.py
yamlgrep/main.py
yamlgrep-0.2.0.dist-info/WHEEL
yamlgrep-0.2.0.dist-info/entry_points.txt
yamlgrep-0.2.0.dist-info/METADATA
yamlgrep-0.2.0.dist-info/RECORD
