Metadata-Version: 2.3
Name: yamlgrep
Version: 0.2.0
Summary: Dumb little tool to 'grep' yaml files
Requires-Dist: pyyaml>=6.0.2
Requires-Dist: rich>=14.1.0
Requires-Dist: rich-argparse>=1.7.1
Requires-Python: >=3.12
